{"config_id": "c05_replay_150_0173__c05_full_eta080_m060_etahet20260832", "rows": [{"instance_id": "c05_replay_150_0173", "campus": 5, "size": 150, "track": "replay", "structure": "full", "phi": null, "eta": 0.8, "m": 0.6, "u_target": null, "u_realized": null, "method": "edd", "seed": 301, "twt": 0.0, "makespan": 27.0, "mean_flow": 2.7283333333333335, "breach_share": 0.0, "breach_p1": null, "breach_p2": null, "breach_p3": 0.0, "breach_p4": 0.0, "decisions": 150, "latency_ms_per_decision": 0.014206574608882269, "replans": null, "validator_ok": 1, "runtime_s": 0.0021309861913323402, "draw_seed": 20260832, "mean_eta": 0.8175506120841768}, {"instance_id": "c05_replay_150_0173", "campus": 5, "size": 150, "track": "replay", "structure": "full", "phi": null, "eta": 0.8, "m": 0.6, "u_target": null, "u_realized": null, "method": "wspt", "seed": 301, "twt": 0.0, "makespan": 27.0, "mean_flow": 2.7260666666666666, "breach_share": 0.0, "breach_p1": null, "breach_p2": null, "breach_p3": 0.0, "breach_p4": 0.0, "decisions": 150, "latency_ms_per_decision": 0.02944828321536382, "replans": null, "validator_ok": 1, "runtime_s": 0.004417242482304573, "draw_seed": 20260832, "mean_eta": 0.8175506120841768}, {"instance_id": "c05_replay_150_0173", "campus": 5, "size": 150, "track": "replay", "structure": "full", "phi": null, "eta": 0.8, "m": 0.6, "u_target": null, "u_realized": null, "method": "atc", "seed": 301, "twt": 0.0, "makespan": 27.0, "mean_flow": 2.7283333333333335, "breach_share": 0.0, "breach_p1": null, "breach_p2": null, "breach_p3": 0.0, "breach_p4": 0.0, "decisions": 150, "latency_ms_per_decision": 0.015533523013194403, "replans": null, "validator_ok": 1, "runtime_s": 0.0023300284519791603, "draw_seed": 20260832, "mean_eta": 0.8175506120841768}, {"instance_id": "c05_replay_150_0173", "campus": 5, "size": 150, "track": "replay", "structure": "full", "phi": null, "eta": 0.8, "m": 0.6, "u_target": null, "u_realized": null, "method": "pfifo", "seed": 301, "twt": 0.0, "makespan": 27.0, "mean_flow": 2.7283333333333335, "breach_share": 0.0, "breach_p1": null, "breach_p2": null, "breach_p3": 0.0, "breach_p4": 0.0, "decisions": 150, "latency_ms_per_decision": 0.013514738529920578, "replans": null, "validator_ok": 1, "runtime_s": 0.0020272107794880867, "draw_seed": 20260832, "mean_eta": 0.8175506120841768}, {"instance_id": "c05_replay_150_0173", "campus": 5, "size": 150, "track": "replay", "structure": "full", "phi": null, "eta": 0.8, "m": 0.6, "u_target": null, "u_realized": null, "method": "mor", "seed": 301, "twt": 0.0, "makespan": 27.0, "mean_flow": 2.7244, "breach_share": 0.0, "breach_p1": null, "breach_p2": null, "breach_p3": 0.0, "breach_p4": 0.0, "decisions": 150, "latency_ms_per_decision": 0.013494609544674555, "replans": null, "validator_ok": 1, "runtime_s": 0.0020241914317011833, "draw_seed": 20260832, "mean_eta": 0.8175506120841768}, {"instance_id": "c05_replay_150_0173", "campus": 5, "size": 150, "track": "replay", "structure": "full", "phi": null, "eta": 0.8, "m": 0.6, "u_target": null, "u_realized": null, "method": "lfj_atc", "seed": 301, "twt": 0.0, "makespan": 27.0, "mean_flow": 2.7283333333333335, "breach_share": 0.0, "breach_p1": null, "breach_p2": null, "breach_p3": 0.0, "breach_p4": 0.0, "decisions": 150, "latency_ms_per_decision": 0.016457388798395794, "replans": null, "validator_ok": 1, "runtime_s": 0.002468608319759369, "draw_seed": 20260832, "mean_eta": 0.8175506120841768}, {"instance_id": "c05_replay_150_0173", "campus": 5, "size": 150, "track": "replay", "structure": "full", "phi": null, "eta": 0.8, "m": 0.6, "u_target": null, "u_realized": null, "method": "atc_eta", "seed": 301, "twt": 0.0, "makespan": 27.0, "mean_flow": 2.7283333333333335, "breach_share": 0.0, "breach_p1": null, "breach_p2": null, "breach_p3": 0.0, "breach_p4": 0.0, "decisions": 150, "latency_ms_per_decision": 0.03632859016458193, "replans": null, "validator_ok": 1, "runtime_s": 0.00544928852468729, "draw_seed": 20260832, "mean_eta": 0.8175506120841768}, {"instance_id": "c05_replay_150_0173", "campus": 5, "size": 150, "track": "replay", "structure": "full", "phi": null, "eta": 0.8, "m": 0.6, "u_target": null, "u_realized": null, "method": "random", "seed": 301, "twt": 0.0, "makespan": 27.0, "mean_flow": 2.7260666666666666, "breach_share": 0.0, "breach_p1": null, "breach_p2": null, "breach_p3": 0.0, "breach_p4": 0.0, "decisions": 150, "latency_ms_per_decision": 0.013827147583166758, "replans": null, "validator_ok": 1, "runtime_s": 0.0020740721374750137, "draw_seed": 20260832, "mean_eta": 0.8175506120841768}]}