{"config_id": "c09_replay_150_0111__perm20260805", "rows": {"edd": {"variant": "perm20260805", "instance_id": "c09_replay_150_0111", "campus": 9, "size": 150, "track": "replay", "structure": "chain", "phi": 1.0, "eta": 1.0, "m": 0.6, "u_target": null, "u_realized": null, "method": "edd", "seed": 301, "twt": 0.0, "makespan": 41.5, "mean_flow": 3.4756666666666667, "breach_share": 0.0, "breach_p1": 0.0, "breach_p2": 0.0, "breach_p3": 0.0, "breach_p4": 0.0, "decisions": 150, "latency_ms_per_decision": 0.007676860938469569, "replans": null, "validator_ok": 1, "runtime_s": 0.0011515291407704353}, "wspt": {"variant": "perm20260805", "instance_id": "c09_replay_150_0111", "campus": 9, "size": 150, "track": "replay", "structure": "chain", "phi": 1.0, "eta": 1.0, "m": 0.6, "u_target": null, "u_realized": null, "method": "wspt", "seed": 301, "twt": 0.0, "makespan": 41.5, "mean_flow": 3.475333333333333, "breach_share": 0.0, "breach_p1": 0.0, "breach_p2": 0.0, "breach_p3": 0.0, "breach_p4": 0.0, "decisions": 150, "latency_ms_per_decision": 0.0478962870935599, "replans": null, "validator_ok": 1, "runtime_s": 0.007184443064033985}, "atc": {"variant": "perm20260805", "instance_id": "c09_replay_150_0111", "campus": 9, "size": 150, "track": "replay", "structure": "chain", "phi": 1.0, "eta": 1.0, "m": 0.6, "u_target": null, "u_realized": null, "method": "atc", "seed": 301, "twt": 0.0, "makespan": 41.5, "mean_flow": 3.4786666666666664, "breach_share": 0.0, "breach_p1": 0.0, "breach_p2": 0.0, "breach_p3": 0.0, "breach_p4": 0.0, "decisions": 150, "latency_ms_per_decision": 0.00979054719209671, "replans": null, "validator_ok": 1, "runtime_s": 0.0014685820788145065}, "pfifo": {"variant": "perm20260805", "instance_id": "c09_replay_150_0111", "campus": 9, "size": 150, "track": "replay", "structure": "chain", "phi": 1.0, "eta": 1.0, "m": 0.6, "u_target": null, "u_realized": null, "method": "pfifo", "seed": 301, "twt": 0.0, "makespan": 41.5, "mean_flow": 3.4756666666666667, "breach_share": 0.0, "breach_p1": 0.0, "breach_p2": 0.0, "breach_p3": 0.0, "breach_p4": 0.0, "decisions": 150, "latency_ms_per_decision": 0.04788703595598539, "replans": null, "validator_ok": 1, "runtime_s": 0.007183055393397808}, "mor": {"variant": "perm20260805", "instance_id": "c09_replay_150_0111", "campus": 9, "size": 150, "track": "replay", "structure": "chain", "phi": 1.0, "eta": 1.0, "m": 0.6, "u_target": null, "u_realized": null, "method": "mor", "seed": 301, "twt": 0.0, "makespan": 39.5, "mean_flow": 3.554333333333333, "breach_share": 0.0, "breach_p1": 0.0, "breach_p2": 0.0, "breach_p3": 0.0, "breach_p4": 0.0, "decisions": 150, "latency_ms_per_decision": 0.007628345241149266, "replans": null, "validator_ok": 1, "runtime_s": 0.00114425178617239}, "lfj_atc": {"variant": "perm20260805", "instance_id": "c09_replay_150_0111", "campus": 9, "size": 150, "track": "replay", "structure": "chain", "phi": 1.0, "eta": 1.0, "m": 0.6, "u_target": null, "u_realized": null, "method": "lfj_atc", "seed": 301, "twt": 0.0, "makespan": 41.5, "mean_flow": 3.4786666666666664, "breach_share": 0.0, "breach_p1": 0.0, "breach_p2": 0.0, "breach_p3": 0.0, "breach_p4": 0.0, "decisions": 150, "latency_ms_per_decision": 0.05093890552719434, "replans": null, "validator_ok": 1, "runtime_s": 0.007640835829079151}, "atc_eta": {"variant": "perm20260805", "instance_id": "c09_replay_150_0111", "campus": 9, "size": 150, "track": "replay", "structure": "chain", "phi": 1.0, "eta": 1.0, "m": 0.6, "u_target": null, "u_realized": null, "method": "atc_eta", "seed": 301, "twt": 0.0, "makespan": 41.5, "mean_flow": 3.4786666666666664, "breach_share": 0.0, "breach_p1": 0.0, "breach_p2": 0.0, "breach_p3": 0.0, "breach_p4": 0.0, "decisions": 150, "latency_ms_per_decision": 0.0742101048429807, "replans": null, "validator_ok": 1, "runtime_s": 0.011131515726447105}, "random": {"variant": "perm20260805", "instance_id": "c09_replay_150_0111", "campus": 9, "size": 150, "track": "replay", "structure": "chain", "phi": 1.0, "eta": 1.0, "m": 0.6, "u_target": null, "u_realized": null, "method": "random", "seed": 301, "twt": 0.0, "makespan": 41.5, "mean_flow": 3.4719999999999995, "breach_share": 0.0, "breach_p1": 0.0, "breach_p2": 0.0, "breach_p3": 0.0, "breach_p4": 0.0, "decisions": 150, "latency_ms_per_decision": 0.007506577918926875, "replans": null, "validator_ok": 1, "runtime_s": 0.0011259866878390312}}, "budget_B": 60, "headcount": 60, "chain_order": ["D40", "D90", "C30", "D30", "D50", "C10", "E10", "B30", "D10", "B20", "D20", "E20", "MISC"]}