{"config_id": "c09_replay_150_0120__tsel20260823", "rows": {"edd": {"variant": "tsel20260823", "instance_id": "c09_replay_150_0120", "campus": 9, "size": 150, "track": "replay", "structure": "chain", "phi": 0.5, "eta": 1.0, "m": 0.6, "u_target": null, "u_realized": null, "method": "edd", "seed": 301, "twt": 216.0, "makespan": 78.0, "mean_flow": 4.099222666666666, "breach_share": 0.006666666666666667, "breach_p1": 0.0, "breach_p2": 0.02040816326530612, "breach_p3": null, "breach_p4": 0.0, "decisions": 150, "latency_ms_per_decision": 0.009526964277029037, "replans": null, "validator_ok": 1, "runtime_s": 0.0014290446415543556}, "wspt": {"variant": "tsel20260823", "instance_id": "c09_replay_150_0120", "campus": 9, "size": 150, "track": "replay", "structure": "chain", "phi": 0.5, "eta": 1.0, "m": 0.6, "u_target": null, "u_realized": null, "method": "wspt", "seed": 301, "twt": 216.0, "makespan": 78.0, "mean_flow": 4.077444666666667, "breach_share": 0.006666666666666667, "breach_p1": 0.0, "breach_p2": 0.02040816326530612, "breach_p3": null, "breach_p4": 0.0, "decisions": 150, "latency_ms_per_decision": 0.030486267060041428, "replans": null, "validator_ok": 1, "runtime_s": 0.004572940059006214}, "atc": {"variant": "tsel20260823", "instance_id": "c09_replay_150_0120", "campus": 9, "size": 150, "track": "replay", "structure": "chain", "phi": 0.5, "eta": 1.0, "m": 0.6, "u_target": null, "u_realized": null, "method": "atc", "seed": 301, "twt": 216.0, "makespan": 78.0, "mean_flow": 4.109889333333334, "breach_share": 0.006666666666666667, "breach_p1": 0.0, "breach_p2": 0.02040816326530612, "breach_p3": null, "breach_p4": 0.0, "decisions": 150, "latency_ms_per_decision": 0.03513605644305547, "replans": null, "validator_ok": 1, "runtime_s": 0.005270408466458321}, "pfifo": {"variant": "tsel20260823", "instance_id": "c09_replay_150_0120", "campus": 9, "size": 150, "track": "replay", "structure": "chain", "phi": 0.5, "eta": 1.0, "m": 0.6, "u_target": null, "u_realized": null, "method": "pfifo", "seed": 301, "twt": 216.0, "makespan": 78.0, "mean_flow": 4.099222666666666, "breach_share": 0.006666666666666667, "breach_p1": 0.0, "breach_p2": 0.02040816326530612, "breach_p3": null, "breach_p4": 0.0, "decisions": 150, "latency_ms_per_decision": 0.009802933782339096, "replans": null, "validator_ok": 1, "runtime_s": 0.0014704400673508644}, "mor": {"variant": "tsel20260823", "instance_id": "c09_replay_150_0120", "campus": 9, "size": 150, "track": "replay", "structure": "chain", "phi": 0.5, "eta": 1.0, "m": 0.6, "u_target": null, "u_realized": null, "method": "mor", "seed": 301, "twt": 216.0, "makespan": 78.0, "mean_flow": 4.246889333333334, "breach_share": 0.006666666666666667, "breach_p1": 0.0, "breach_p2": 0.02040816326530612, "breach_p3": null, "breach_p4": 0.0, "decisions": 150, "latency_ms_per_decision": 0.009793490171432495, "replans": null, "validator_ok": 1, "runtime_s": 0.0014690235257148743}, "lfj_atc": {"variant": "tsel20260823", "instance_id": "c09_replay_150_0120", "campus": 9, "size": 150, "track": "replay", "structure": "chain", "phi": 0.5, "eta": 1.0, "m": 0.6, "u_target": null, "u_realized": null, "method": "lfj_atc", "seed": 301, "twt": 216.0, "makespan": 78.0, "mean_flow": 4.109889333333334, "breach_share": 0.006666666666666667, "breach_p1": 0.0, "breach_p2": 0.02040816326530612, "breach_p3": null, "breach_p4": 0.0, "decisions": 150, "latency_ms_per_decision": 0.036330390721559525, "replans": null, "validator_ok": 1, "runtime_s": 0.005449558608233929}, "atc_eta": {"variant": "tsel20260823", "instance_id": "c09_replay_150_0120", "campus": 9, "size": 150, "track": "replay", "structure": "chain", "phi": 0.5, "eta": 1.0, "m": 0.6, "u_target": null, "u_realized": null, "method": "atc_eta", "seed": 301, "twt": 216.0, "makespan": 78.0, "mean_flow": 4.109889333333334, "breach_share": 0.006666666666666667, "breach_p1": 0.0, "breach_p2": 0.02040816326530612, "breach_p3": null, "breach_p4": 0.0, "decisions": 150, "latency_ms_per_decision": 0.07104393094778061, "replans": null, "validator_ok": 1, "runtime_s": 0.010656589642167091}, "random": {"variant": "tsel20260823", "instance_id": "c09_replay_150_0120", "campus": 9, "size": 150, "track": "replay", "structure": "chain", "phi": 0.5, "eta": 1.0, "m": 0.6, "u_target": null, "u_realized": null, "method": "random", "seed": 301, "twt": 216.0, "makespan": 78.0, "mean_flow": 4.114889333333334, "breach_share": 0.006666666666666667, "breach_p1": 0.0, "breach_p2": 0.02040816326530612, "breach_p3": null, "breach_p4": 0.0, "decisions": 150, "latency_ms_per_decision": 0.00844411551952362, "replans": null, "validator_ok": 1, "runtime_s": 0.001266617327928543}}, "budget_B": 34, "headcount": 60, "chain_order": ["D30", "D50", "D20", "D40", "D90", "C30", "E10", "B30", "MISC", "C10", "B20", "E20", "D10"]}