{"config_id": "c12_replay_400_0159__chain_adj_eta080", "rows": {"edd": {"variant": "chain_adj", "instance_id": "c12_replay_400_0159", "campus": 12, "size": 400, "track": "replay", "structure": "chain_adj", "phi": 1.0, "eta": 0.8, "m": 0.6, "u_target": null, "u_realized": null, "method": "edd", "seed": 301, "twt": 658.1024, "makespan": 115.24090000000001, "mean_flow": 6.2867795, "breach_share": 0.0225, "breach_p1": 0.14285714285714285, "breach_p2": 0.015625, "breach_p3": 0.0, "breach_p4": 0.0, "decisions": 400, "latency_ms_per_decision": 0.03874889574944973, "replans": null, "validator_ok": 1, "runtime_s": 0.015499558299779892}, "wspt": {"variant": "chain_adj", "instance_id": "c12_replay_400_0159", "campus": 12, "size": 400, "track": "replay", "structure": "chain_adj", "phi": 1.0, "eta": 0.8, "m": 0.6, "u_target": null, "u_realized": null, "method": "wspt", "seed": 301, "twt": 658.0, "makespan": 115.24090000000001, "mean_flow": 6.2870415, "breach_share": 0.02, "breach_p1": 0.125, "breach_p2": 0.015625, "breach_p3": 0.0, "breach_p4": 0.0, "decisions": 400, "latency_ms_per_decision": 0.023759182076901197, "replans": null, "validator_ok": 1, "runtime_s": 0.009503672830760479}, "atc": {"variant": "chain_adj", "instance_id": "c12_replay_400_0159", "campus": 12, "size": 400, "track": "replay", "structure": "chain_adj", "phi": 1.0, "eta": 0.8, "m": 0.6, "u_target": null, "u_realized": null, "method": "atc", "seed": 301, "twt": 658.0, "makespan": 115.24090000000001, "mean_flow": 6.26919625, "breach_share": 0.02, "breach_p1": 0.125, "breach_p2": 0.015625, "breach_p3": 0.0, "breach_p4": 0.0, "decisions": 400, "latency_ms_per_decision": 0.02574334852397442, "replans": null, "validator_ok": 1, "runtime_s": 0.010297339409589767}, "pfifo": {"variant": "chain_adj", "instance_id": "c12_replay_400_0159", "campus": 12, "size": 400, "track": "replay", "structure": "chain_adj", "phi": 1.0, "eta": 0.8, "m": 0.6, "u_target": null, "u_realized": null, "method": "pfifo", "seed": 301, "twt": 658.1024, "makespan": 115.24090000000001, "mean_flow": 6.2867795, "breach_share": 0.0225, "breach_p1": 0.14285714285714285, "breach_p2": 0.015625, "breach_p3": 0.0, "breach_p4": 0.0, "decisions": 400, "latency_ms_per_decision": 0.02388002583757043, "replans": null, "validator_ok": 1, "runtime_s": 0.009552010335028172}, "mor": {"variant": "chain_adj", "instance_id": "c12_replay_400_0159", "campus": 12, "size": 400, "track": "replay", "structure": "chain_adj", "phi": 1.0, "eta": 0.8, "m": 0.6, "u_target": null, "u_realized": null, "method": "mor", "seed": 301, "twt": 658.1024, "makespan": 115.24090000000001, "mean_flow": 6.2603557499999996, "breach_share": 0.0225, "breach_p1": 0.14285714285714285, "breach_p2": 0.015625, "breach_p3": 0.0, "breach_p4": 0.0, "decisions": 400, "latency_ms_per_decision": 0.023512572515755892, "replans": null, "validator_ok": 1, "runtime_s": 0.009405029006302357}, "lfj_atc": {"variant": "chain_adj", "instance_id": "c12_replay_400_0159", "campus": 12, "size": 400, "track": "replay", "structure": "chain_adj", "phi": 1.0, "eta": 0.8, "m": 0.6, "u_target": null, "u_realized": null, "method": "lfj_atc", "seed": 301, "twt": 658.0, "makespan": 115.24090000000001, "mean_flow": 6.26919625, "breach_share": 0.02, "breach_p1": 0.125, "breach_p2": 0.015625, "breach_p3": 0.0, "breach_p4": 0.0, "decisions": 400, "latency_ms_per_decision": 0.029509086161851883, "replans": null, "validator_ok": 1, "runtime_s": 0.011803634464740753}, "atc_eta": {"variant": "chain_adj", "instance_id": "c12_replay_400_0159", "campus": 12, "size": 400, "track": "replay", "structure": "chain_adj", "phi": 1.0, "eta": 0.8, "m": 0.6, "u_target": null, "u_realized": null, "method": "atc_eta", "seed": 301, "twt": 658.0, "makespan": 115.24090000000001, "mean_flow": 6.26919625, "breach_share": 0.02, "breach_p1": 0.125, "breach_p2": 0.015625, "breach_p3": 0.0, "breach_p4": 0.0, "decisions": 400, "latency_ms_per_decision": 0.045483841095119715, "replans": null, "validator_ok": 1, "runtime_s": 0.018193536438047886}, "random": {"variant": "chain_adj", "instance_id": "c12_replay_400_0159", "campus": 12, "size": 400, "track": "replay", "structure": "chain_adj", "phi": 1.0, "eta": 0.8, "m": 0.6, "u_target": null, "u_realized": null, "method": "random", "seed": 301, "twt": 681.76, "makespan": 115.24090000000001, "mean_flow": 6.2835435, "breach_share": 0.025, "breach_p1": 0.14285714285714285, "breach_p2": 0.03125, "breach_p3": 0.0, "breach_p4": 0.0, "decisions": 400, "latency_ms_per_decision": 0.015702357050031424, "replans": null, "validator_ok": 1, "runtime_s": 0.006280942820012569}}, "budget_B": 112, "headcount": 112, "chain_order": ["D30", "D20", "D90", "D40", "MISC", "E20", "E10", "UNK", "C30", "C10", "D50", "B20", "B30"]}