{"config_id": "c10_replay_400_0117__c10_chain_phi050_eta080_m100", "rows": {"edd": {"instance_id": "c10_replay_400_0117", "campus": 10, "size": 400, "track": "replay", "structure": "chain", "phi": 0.5, "eta": 0.8, "m": 1.0, "u_target": null, "u_realized": null, "method": "edd", "seed": 301, "twt": 226.0, "makespan": 115.47, "mean_flow": 5.0831877500000004, "breach_share": 0.005, "breach_p1": 0.09090909090909091, "breach_p2": 0.034482758620689655, "breach_p3": 0.0, "breach_p4": 0.0, "decisions": 400, "latency_ms_per_decision": 0.011379048228263855, "replans": null, "validator_ok": 1, "runtime_s": 0.004551619291305542}, "wspt": {"instance_id": "c10_replay_400_0117", "campus": 10, "size": 400, "track": "replay", "structure": "chain", "phi": 0.5, "eta": 0.8, "m": 1.0, "u_target": null, "u_realized": null, "method": "wspt", "seed": 301, "twt": 231.51999999999998, "makespan": 115.16, "mean_flow": 4.901567750000001, "breach_share": 0.005, "breach_p1": 0.09090909090909091, "breach_p2": 0.034482758620689655, "breach_p3": 0.0, "breach_p4": 0.0, "decisions": 400, "latency_ms_per_decision": 0.012143977219238877, "replans": null, "validator_ok": 1, "runtime_s": 0.004857590887695551}, "atc": {"instance_id": "c10_replay_400_0117", "campus": 10, "size": 400, "track": "replay", "structure": "chain", "phi": 0.5, "eta": 0.8, "m": 1.0, "u_target": null, "u_realized": null, "method": "atc", "seed": 301, "twt": 226.0, "makespan": 94.97200000000001, "mean_flow": 4.970370249999999, "breach_share": 0.005, "breach_p1": 0.09090909090909091, "breach_p2": 0.034482758620689655, "breach_p3": 0.0, "breach_p4": 0.0, "decisions": 400, "latency_ms_per_decision": 0.020374144660308957, "replans": null, "validator_ok": 1, "runtime_s": 0.008149657864123583}, "pfifo": {"instance_id": "c10_replay_400_0117", "campus": 10, "size": 400, "track": "replay", "structure": "chain", "phi": 0.5, "eta": 0.8, "m": 1.0, "u_target": null, "u_realized": null, "method": "pfifo", "seed": 301, "twt": 226.0, "makespan": 115.47, "mean_flow": 5.0831877500000004, "breach_share": 0.005, "breach_p1": 0.09090909090909091, "breach_p2": 0.034482758620689655, "breach_p3": 0.0, "breach_p4": 0.0, "decisions": 400, "latency_ms_per_decision": 0.013156867353245616, "replans": null, "validator_ok": 1, "runtime_s": 0.005262746941298246}, "mor": {"instance_id": "c10_replay_400_0117", "campus": 10, "size": 400, "track": "replay", "structure": "chain", "phi": 0.5, "eta": 0.8, "m": 1.0, "u_target": null, "u_realized": null, "method": "mor", "seed": 301, "twt": 226.0, "makespan": 94.97200000000001, "mean_flow": 5.3254157499999994, "breach_share": 0.005, "breach_p1": 0.09090909090909091, "breach_p2": 0.034482758620689655, "breach_p3": 0.0, "breach_p4": 0.0, "decisions": 400, "latency_ms_per_decision": 0.011415070621296763, "replans": null, "validator_ok": 1, "runtime_s": 0.004566028248518705}, "lfj_atc": {"instance_id": "c10_replay_400_0117", "campus": 10, "size": 400, "track": "replay", "structure": "chain", "phi": 0.5, "eta": 0.8, "m": 1.0, "u_target": null, "u_realized": null, "method": "lfj_atc", "seed": 301, "twt": 226.0, "makespan": 94.97200000000001, "mean_flow": 4.970370249999999, "breach_share": 0.005, "breach_p1": 0.09090909090909091, "breach_p2": 0.034482758620689655, "breach_p3": 0.0, "breach_p4": 0.0, "decisions": 400, "latency_ms_per_decision": 0.022481553023681045, "replans": null, "validator_ok": 1, "runtime_s": 0.008992621209472418}, "atc_eta": {"instance_id": "c10_replay_400_0117", "campus": 10, "size": 400, "track": "replay", "structure": "chain", "phi": 0.5, "eta": 0.8, "m": 1.0, "u_target": null, "u_realized": null, "method": "atc_eta", "seed": 301, "twt": 226.0, "makespan": 94.97200000000001, "mean_flow": 4.970370249999999, "breach_share": 0.005, "breach_p1": 0.09090909090909091, "breach_p2": 0.034482758620689655, "breach_p3": 0.0, "breach_p4": 0.0, "decisions": 400, "latency_ms_per_decision": 0.03706312971189618, "replans": null, "validator_ok": 1, "runtime_s": 0.014825251884758472}, "random": {"instance_id": "c10_replay_400_0117", "campus": 10, "size": 400, "track": "replay", "structure": "chain", "phi": 0.5, "eta": 0.8, "m": 1.0, "u_target": null, "u_realized": null, "method": "random", "seed": 301, "twt": 226.0, "makespan": 94.97200000000001, "mean_flow": 4.99914725, "breach_share": 0.005, "breach_p1": 0.09090909090909091, "breach_p2": 0.034482758620689655, "breach_p3": 0.0, "breach_p4": 0.0, "decisions": 400, "latency_ms_per_decision": 0.00783315277658403, "replans": null, "validator_ok": 1, "runtime_s": 0.0031332611106336117}, "v2mlp301": {"instance_id": "c10_replay_400_0117", "campus": 10, "size": 400, "track": "replay", "structure": "chain", "phi": 0.5, "eta": 0.8, "m": 1.0, "u_target": null, "u_realized": null, "method": "v2mlp301", "seed": 301, "twt": 226.0, "makespan": 117.69720000000001, "mean_flow": 5.008370500000001, "breach_share": 0.005, "breach_p1": 0.09090909090909091, "breach_p2": 0.034482758620689655, "breach_p3": 0.0, "breach_p4": 0.0, "decisions": 400, "latency_ms_per_decision": 0.5140112922526896, "replans": null, "validator_ok": 1, "runtime_s": 0.20560451690107584}, "v2mlp302": {"instance_id": "c10_replay_400_0117", "campus": 10, "size": 400, "track": "replay", "structure": "chain", "phi": 0.5, "eta": 0.8, "m": 1.0, "u_target": null, "u_realized": null, "method": "v2mlp302", "seed": 302, "twt": 226.0, "makespan": 117.6967, "mean_flow": 5.2010795, "breach_share": 0.005, "breach_p1": 0.09090909090909091, "breach_p2": 0.034482758620689655, "breach_p3": 0.0, "breach_p4": 0.0, "decisions": 400, "latency_ms_per_decision": 0.841529545141384, "replans": null, "validator_ok": 1, "runtime_s": 0.3366118180565536}, "v2mlp303": {"instance_id": "c10_replay_400_0117", "campus": 10, "size": 400, "track": "replay", "structure": "chain", "phi": 0.5, "eta": 0.8, "m": 1.0, "u_target": null, "u_realized": null, "method": "v2mlp303", "seed": 303, "twt": 226.0, "makespan": 95.3648, "mean_flow": 5.267176999999999, "breach_share": 0.005, "breach_p1": 0.09090909090909091, "breach_p2": 0.034482758620689655, "breach_p3": 0.0, "breach_p4": 0.0, "decisions": 400, "latency_ms_per_decision": 1.4189931529108435, "replans": null, "validator_ok": 1, "runtime_s": 0.5675972611643374}, "v2mlp304": {"instance_id": "c10_replay_400_0117", "campus": 10, "size": 400, "track": "replay", "structure": "chain", "phi": 0.5, "eta": 0.8, "m": 1.0, "u_target": null, "u_realized": null, "method": "v2mlp304", "seed": 304, "twt": 226.0, "makespan": 117.69720000000001, "mean_flow": 5.3762697500000005, "breach_share": 0.005, "breach_p1": 0.09090909090909091, "breach_p2": 0.034482758620689655, "breach_p3": 0.0, "breach_p4": 0.0, "decisions": 400, "latency_ms_per_decision": 0.5525967583525926, "replans": null, "validator_ok": 1, "runtime_s": 0.22103870334103703}, "v2mlp305": {"instance_id": "c10_replay_400_0117", "campus": 10, "size": 400, "track": "replay", "structure": "chain", "phi": 0.5, "eta": 0.8, "m": 1.0, "u_target": null, "u_realized": null, "method": "v2mlp305", "seed": 305, "twt": 226.0, "makespan": 94.97200000000001, "mean_flow": 4.90180375, "breach_share": 0.005, "breach_p1": 0.09090909090909091, "breach_p2": 0.034482758620689655, "breach_p3": 0.0, "breach_p4": 0.0, "decisions": 400, "latency_ms_per_decision": 0.5173939489759505, "replans": null, "validator_ok": 1, "runtime_s": 0.2069575795903802}, "v2mlp306": {"instance_id": "c10_replay_400_0117", "campus": 10, "size": 400, "track": "replay", "structure": "chain", "phi": 0.5, "eta": 0.8, "m": 1.0, "u_target": null, "u_realized": null, "method": "v2mlp306", "seed": 306, "twt": 226.0, "makespan": 117.84, "mean_flow": 5.457480499999999, "breach_share": 0.005, "breach_p1": 0.09090909090909091, "breach_p2": 0.034482758620689655, "breach_p3": 0.0, "breach_p4": 0.0, "decisions": 400, "latency_ms_per_decision": 0.4891356371808797, "replans": null, "validator_ok": 1, "runtime_s": 0.19565425487235188}, "v2mlp307": {"instance_id": "c10_replay_400_0117", "campus": 10, "size": 400, "track": "replay", "structure": "chain", "phi": 0.5, "eta": 0.8, "m": 1.0, "u_target": null, "u_realized": null, "method": "v2mlp307", "seed": 307, "twt": 226.0, "makespan": 95.1148, "mean_flow": 5.41423225, "breach_share": 0.005, "breach_p1": 0.09090909090909091, "breach_p2": 0.034482758620689655, "breach_p3": 0.0, "breach_p4": 0.0, "decisions": 400, "latency_ms_per_decision": 0.5022697953972965, "replans": null, "validator_ok": 1, "runtime_s": 0.20090791815891862}, "v2mlp308": {"instance_id": "c10_replay_400_0117", "campus": 10, "size": 400, "track": "replay", "structure": "chain", "phi": 0.5, "eta": 0.8, "m": 1.0, "u_target": null, "u_realized": null, "method": "v2mlp308", "seed": 308, "twt": 226.0, "makespan": 117.6967, "mean_flow": 5.18466125, "breach_share": 0.005, "breach_p1": 0.09090909090909091, "breach_p2": 0.034482758620689655, "breach_p3": 0.0, "breach_p4": 0.0, "decisions": 400, "latency_ms_per_decision": 0.4851958283688873, "replans": null, "validator_ok": 1, "runtime_s": 0.19407833134755492}, "v2mlp309": {"instance_id": "c10_replay_400_0117", "campus": 10, "size": 400, "track": "replay", "structure": "chain", "phi": 0.5, "eta": 0.8, "m": 1.0, "u_target": null, "u_realized": null, "method": "v2mlp309", "seed": 309, "twt": 226.0, "makespan": 117.03, "mean_flow": 5.8634305, "breach_share": 0.005, "breach_p1": 0.09090909090909091, "breach_p2": 0.034482758620689655, "breach_p3": 0.0, "breach_p4": 0.0, "decisions": 400, "latency_ms_per_decision": 0.6008453830145299, "replans": null, "validator_ok": 1, "runtime_s": 0.24033815320581198}, "v2mlp310": {"instance_id": "c10_replay_400_0117", "campus": 10, "size": 400, "track": "replay", "structure": "chain", "phi": 0.5, "eta": 0.8, "m": 1.0, "u_target": null, "u_realized": null, "method": "v2mlp310", "seed": 310, "twt": 226.0, "makespan": 118.09, "mean_flow": 5.245553749999999, "breach_share": 0.005, "breach_p1": 0.09090909090909091, "breach_p2": 0.034482758620689655, "breach_p3": 0.0, "breach_p4": 0.0, "decisions": 400, "latency_ms_per_decision": 0.6897563918028027, "replans": null, "validator_ok": 1, "runtime_s": 0.2759025567211211}, "v2attn401": {"instance_id": "c10_replay_400_0117", "campus": 10, "size": 400, "track": "replay", "structure": "chain", "phi": 0.5, "eta": 0.8, "m": 1.0, "u_target": null, "u_realized": null, "method": "v2attn401", "seed": 401, "twt": 226.0, "makespan": 117.72, "mean_flow": 5.46865775, "breach_share": 0.005, "breach_p1": 0.09090909090909091, "breach_p2": 0.034482758620689655, "breach_p3": 0.0, "breach_p4": 0.0, "decisions": 400, "latency_ms_per_decision": 1.980280427960679, "replans": null, "validator_ok": 1, "runtime_s": 0.7921121711842716}, "v2attn402": {"instance_id": "c10_replay_400_0117", "campus": 10, "size": 400, "track": "replay", "structure": "chain", "phi": 0.5, "eta": 0.8, "m": 1.0, "u_target": null, "u_realized": null, "method": "v2attn402", "seed": 402, "twt": 226.0, "makespan": 94.97200000000001, "mean_flow": 5.2739025, "breach_share": 0.005, "breach_p1": 0.09090909090909091, "breach_p2": 0.034482758620689655, "breach_p3": 0.0, "breach_p4": 0.0, "decisions": 400, "latency_ms_per_decision": 1.6633607994299382, "replans": null, "validator_ok": 1, "runtime_s": 0.6653443197719753}, "v2attn403": {"instance_id": "c10_replay_400_0117", "campus": 10, "size": 400, "track": "replay", "structure": "chain", "phi": 0.5, "eta": 0.8, "m": 1.0, "u_target": null, "u_realized": null, "method": "v2attn403", "seed": 403, "twt": 226.0, "makespan": 94.97200000000001, "mean_flow": 4.982795500000001, "breach_share": 0.005, "breach_p1": 0.09090909090909091, "breach_p2": 0.034482758620689655, "breach_p3": 0.0, "breach_p4": 0.0, "decisions": 400, "latency_ms_per_decision": 1.1201010504737496, "replans": null, "validator_ok": 1, "runtime_s": 0.44804042018949986}, "v2attn404": {"instance_id": "c10_replay_400_0117", "campus": 10, "size": 400, "track": "replay", "structure": "chain", "phi": 0.5, "eta": 0.8, "m": 1.0, "u_target": null, "u_realized": null, "method": "v2attn404", "seed": 404, "twt": 226.0, "makespan": 94.97200000000001, "mean_flow": 5.107761, "breach_share": 0.005, "breach_p1": 0.09090909090909091, "breach_p2": 0.034482758620689655, "breach_p3": 0.0, "breach_p4": 0.0, "decisions": 400, "latency_ms_per_decision": 1.209845661651343, "replans": null, "validator_ok": 1, "runtime_s": 0.48393826466053724}, "v2attn405": {"instance_id": "c10_replay_400_0117", "campus": 10, "size": 400, "track": "replay", "structure": "chain", "phi": 0.5, "eta": 0.8, "m": 1.0, "u_target": null, "u_realized": null, "method": "v2attn405", "seed": 405, "twt": 226.0, "makespan": 94.97200000000001, "mean_flow": 5.47099175, "breach_share": 0.005, "breach_p1": 0.09090909090909091, "breach_p2": 0.034482758620689655, "breach_p3": 0.0, "breach_p4": 0.0, "decisions": 400, "latency_ms_per_decision": 1.2062041147146374, "replans": null, "validator_ok": 1, "runtime_s": 0.48248164588585496}, "v2attn406": {"instance_id": "c10_replay_400_0117", "campus": 10, "size": 400, "track": "replay", "structure": "chain", "phi": 0.5, "eta": 0.8, "m": 1.0, "u_target": null, "u_realized": null, "method": "v2attn406", "seed": 406, "twt": 300.52, "makespan": 117.69720000000001, "mean_flow": 5.79524725, "breach_share": 0.005, "breach_p1": 0.09090909090909091, "breach_p2": 0.034482758620689655, "breach_p3": 0.0, "breach_p4": 0.0, "decisions": 400, "latency_ms_per_decision": 1.2005410459823906, "replans": null, "validator_ok": 1, "runtime_s": 0.48021641839295626}, "v2attn407": {"instance_id": "c10_replay_400_0117", "campus": 10, "size": 400, "track": "replay", "structure": "chain", "phi": 0.5, "eta": 0.8, "m": 1.0, "u_target": null, "u_realized": null, "method": "v2attn407", "seed": 407, "twt": 226.0, "makespan": 95.1148, "mean_flow": 5.435953999999999, "breach_share": 0.005, "breach_p1": 0.09090909090909091, "breach_p2": 0.034482758620689655, "breach_p3": 0.0, "breach_p4": 0.0, "decisions": 400, "latency_ms_per_decision": 1.3193621672689915, "replans": null, "validator_ok": 1, "runtime_s": 0.5277448669075966}, "v2attn408": {"instance_id": "c10_replay_400_0117", "campus": 10, "size": 400, "track": "replay", "structure": "chain", "phi": 0.5, "eta": 0.8, "m": 1.0, "u_target": null, "u_realized": null, "method": "v2attn408", "seed": 408, "twt": 226.0, "makespan": 94.97200000000001, "mean_flow": 5.062600000000001, "breach_share": 0.005, "breach_p1": 0.09090909090909091, "breach_p2": 0.034482758620689655, "breach_p3": 0.0, "breach_p4": 0.0, "decisions": 400, "latency_ms_per_decision": 1.0397625318728387, "replans": null, "validator_ok": 1, "runtime_s": 0.4159050127491355}, "v2attn409": {"instance_id": "c10_replay_400_0117", "campus": 10, "size": 400, "track": "replay", "structure": "chain", "phi": 0.5, "eta": 0.8, "m": 1.0, "u_target": null, "u_realized": null, "method": "v2attn409", "seed": 409, "twt": 226.0, "makespan": 117.69720000000001, "mean_flow": 5.08495975, "breach_share": 0.005, "breach_p1": 0.09090909090909091, "breach_p2": 0.034482758620689655, "breach_p3": 0.0, "breach_p4": 0.0, "decisions": 400, "latency_ms_per_decision": 1.4109625725541264, "replans": null, "validator_ok": 1, "runtime_s": 0.5643850290216506}, "v2attn410": {"instance_id": "c10_replay_400_0117", "campus": 10, "size": 400, "track": "replay", "structure": "chain", "phi": 0.5, "eta": 0.8, "m": 1.0, "u_target": null, "u_realized": null, "method": "v2attn410", "seed": 410, "twt": 226.0, "makespan": 94.97200000000001, "mean_flow": 5.13544075, "breach_share": 0.005, "breach_p1": 0.09090909090909091, "breach_p2": 0.034482758620689655, "breach_p3": 0.0, "breach_p4": 0.0, "decisions": 400, "latency_ms_per_decision": 1.9972752081230283, "replans": null, "validator_ok": 1, "runtime_s": 0.7989100832492113}}, "methods_expected": ["atc", "atc_eta", "edd", "lfj_atc", "mor", "pfifo", "random", "v2attn401", "v2attn402", "v2attn403", "v2attn404", "v2attn405", "v2attn406", "v2attn407", "v2attn408", "v2attn409", "v2attn410", "v2mlp301", "v2mlp302", "v2mlp303", "v2mlp304", "v2mlp305", "v2mlp306", "v2mlp307", "v2mlp308", "v2mlp309", "v2mlp310", "wspt"], "wall_seconds_total": 8.321775769814849}